setup.py
carbonite/__init__.py
carbonite/freeze.py
carbonite.egg-info/PKG-INFO
carbonite.egg-info/SOURCES.txt
carbonite.egg-info/dependency_links.txt
carbonite.egg-info/entry_points.txt
carbonite.egg-info/not-zip-safe
carbonite.egg-info/requires.txt
carbonite.egg-info/top_level.txt