Metadata-Version: 1.0
Name: carbonite
Version: 0.0.7
Summary: Freeze your Python package dependencies
Home-page: https://github.com/gamechanger/carbonite
Author: GameChanger
Author-email: kiril@gc.io
License: MIT
Platform: UNKNOWN
